jugalbandi/jugalbandi.py
jugalbandi-0.1.dist-info/METADATA
jugalbandi-0.1.dist-info/WHEEL
jugalbandi-0.1.dist-info/top_level.txt
jugalbandi-0.1.dist-info/RECORD
