Metadata-Version: 2.1
Name: jugalbandi
Version: 0.1
Summary: Client side SDK to build applications using Jugalbandi
Author: Saurabh Kumar Karn
Author-email: saurabh@agami.in
Requires-Dist: requests
